structured_prompt/__init__.py
structured_prompt/cli.py
structured_prompt/dynamic_prompt_builder.py
structured_prompt/stage_contract.py
structured_prompt/builder/__init__.py
structured_prompt/builder/helpers.py
structured_prompt/builder/items.py
structured_prompt/builder/preferences.py
structured_prompt/builder/sections.py
structured_prompt/builder/structured_prompt_factory.py
structured_prompt/generator/__init__.py
structured_prompt/generator/prompt_structure_generator.py
structured_prompt-0.2.1.dist-info/licenses/LICENSE
structured_prompt-0.2.1.dist-info/METADATA
structured_prompt-0.2.1.dist-info/WHEEL
structured_prompt-0.2.1.dist-info/entry_points.txt
structured_prompt-0.2.1.dist-info/top_level.txt
structured_prompt-0.2.1.dist-info/RECORD
