Metadata-Version: 2.4
Name: structured-prompt
Version: 0.2.1
Summary: A framework for creating extensible, reusable, and standardized prompts
Author: Model Labs
License: MIT License
Project-URL: Homepage, https://github.com/model-labs/structured-prompt
Project-URL: Repository, https://github.com/model-labs/structured-prompt
Project-URL: Issues, https://github.com/model-labs/structured-prompt/issues
Keywords: prompt,llm,ai,prompt-engineering,structured-prompts
Classifier: Development Status :: 3 - Alpha
Classifier: Intended Audience :: Developers
Classifier: License :: OSI Approved :: MIT License
Classifier: Programming Language :: Python :: 3
Classifier: Programming Language :: Python :: 3.8
Classifier: Programming Language :: Python :: 3.9
Classifier: Programming Language :: Python :: 3.10
Classifier: Programming Language :: Python :: 3.11
Classifier: Programming Language :: Python :: 3.12
Requires-Python: >=3.8
License-File: LICENSE
Requires-Dist: PyYAML>=6.0
Provides-Extra: dev
Requires-Dist: pytest>=7.0; extra == "dev"
Requires-Dist: ruff>=0.1.0; extra == "dev"
Requires-Dist: mypy>=1.0; extra == "dev"
Dynamic: license-file
